{
  "ciudades": [
    {
      "peliculas": [
        {
          "titulo": "PITUFOS",
          "horarios": [
            {
              "horario": "10:10",
              "idioma": "Cerrado",
              "formato": "2D - 2D KRONOS"
            },
            {
              "horario": "12:20",
              "idioma": "Cerrado",
              "formato": "2D - 2D KRONOS"
            },
            {
              "horario": "14:30",
              "idioma": "Español",
              "formato": "2D - 2D KRONOS"
            },
            {
              "horario": "16:40",
              "idioma": "Español",
              "formato": "2D - 2D KRONOS"
            },
            {
              "horario": "18:50",
              "idioma": "Español",
              "formato": "2D - 2D KRONOS"
            },
            {
              "horario": "20:50",
              "idioma": "Español",
              "formato": "2D - 2D KRONOS"
            },
            {
              "horario": "22:45",
              "idioma": "Español",
              "formato": "2D - 2D KRONOS"
            },
            {
              "horario": "11:10",
              "idioma": "Cerrado",
              "formato": "2D"
            },
            {
              "horario": "13:20",
              "idioma": "Cerrado",
              "formato": "2D"
            },
            {
              "horario": "15:30",
              "idioma": "Español",
              "formato": "2D"
            },
            {
              "horario": "17:40",
              "idioma": "Español",
              "formato": "2D"
            }
          ],
          "id": "7d985bde-967b-49b8-9eec-77576e44a9de"
        },
        {
          "titulo": "JURASSIC WORLD: RENACE",
          "horarios": [
            {
              "horario": "10:30",
              "idioma": "Cerrado",
              "formato": "3D - 3D KRONOS"
            },
            {
              "horario": "13:10",
              "idioma": "Cerrado",
              "formato": "3D - 3D KRONOS"
            },
            {
              "horario": "15:50",
              "idioma": "Español",
              "formato": "3D - 3D KRONOS"
            },
            {
              "horario": "18:30",
              "idioma": "Español",
              "formato": "3D - 3D KRONOS"
            },
            {
              "horario": "21:10",
              "idioma": "Español",
              "formato": "3D - 3D KRONOS"
            },
            {
              "horario": "11:30",
              "idioma": "Cerrado",
              "formato": "2D - 2D KRONOS"
            },
            {
              "horario": "14:10",
              "idioma": "Español",
              "formato": "2D - 2D KRONOS"
            },
            {
              "horario": "16:50",
              "idioma": "Español",
              "formato": "2D - 2D KRONOS"
            },
            {
              "horario": "19:30",
              "idioma": "Español",
              "formato": "2D - 2D KRONOS"
            },
            {
              "horario": "22:10",
              "idioma": "Español",
              "formato": "2D - 2D KRONOS"
            }
          ],
          "id": "d575a327-ed79-4def-9c45-36eba7299931"
        },
        {
          "titulo": "SUPERMAN",
          "horarios": [
            {
              "horario": "10:00",
              "idioma": "Cerrado",
              "formato": "2D"
            },
            {
              "horario": "12:40",
              "idioma": "Cerrado",
              "formato": "2D"
            },
            {
              "horario": "15:20",
              "idioma": "Español",
              "formato": "2D"
            },
            {
              "horario": "18:00",
              "idioma": "Español",
              "formato": "2D"
            },
            {
              "horario": "20:40",
              "idioma": "Español",
              "formato": "2D"
            },
            {
              "horario": "11:40",
              "idioma": "Cerrado",
              "formato": "3D XL - 3D XL KRONOS"
            },
            {
              "horario": "14:20",
              "idioma": "Español",
              "formato": "3D XL - 3D XL KRONOS"
            },
            {
              "horario": "17:00",
              "idioma": "Español",
              "formato": "3D XL - 3D XL KRONOS"
            },
            {
              "horario": "19:40",
              "idioma": "Español",
              "formato": "3D XL - 3D XL KRONOS"
            },
            {
              "horario": "22:20",
              "idioma": "Español",
              "formato": "3D XL - 3D XL KRONOS"
            }
          ],
          "id": "cef9dde9-82f7-4d3e-b8cc-04c82a7e24fa"
        },
        {
          "titulo": "COMO ENTRENAR A TU DRAGÓN",
          "horarios": [
            {
              "horario": "11:30",
              "idioma": "Cerrado",
              "formato": "2D"
            },
            {
              "horario": "14:00",
              "idioma": "Español",
              "formato": "2D"
            },
            {
              "horario": "16:30",
              "idioma": "Español",
              "formato": "2D"
            },
            {
              "horario": "19:00",
              "idioma": "Español",
              "formato": "2D"
            },
            {
              "horario": "21:30",
              "idioma": "Español",
              "formato": "2D"
            }
          ],
          "id": "89155ab0-b1a2-4bbe-90be-1f122db9ae7b"
        },
        {
          "titulo": "SÉ LO QUE HICIERON EL VERANO PASADO",
          "horarios": [
            {
              "horario": "13:00",
              "idioma": "Cerrado",
              "formato": "2D"
            },
            {
              "horario": "17:45",
              "idioma": "Español",
              "formato": "2D"
            },
            {
              "horario": "20:10",
              "idioma": "Español",
              "formato": "2D"
            },
            {
              "horario": "22:40",
              "idioma": "Español",
              "formato": "2D"
            }
          ],
          "id": "04d184eb-f6f1-44d4-96c3-707849b973d7"
        },
        {
          "titulo": "LILO & STITCH",
          "horarios": [
            {
              "horario": "15:20",
              "idioma": "Español",
              "formato": "2D"
            },
            {
              "horario": "19:50",
              "idioma": "Español",
              "formato": "2D"
            }
          ],
          "id": "54eaac66-627e-4af9-b760-a9d19f3ae083"
        },
        {
          "titulo": "INVASIÓN ZOMBIE: HIJOS DEL APOCALÍPSIS",
          "horarios": [
            {
              "horario": "22:00",
              "idioma": "Español",
              "formato": "2D"
            }
          ],
          "id": "caa7e991-4b8a-4972-bbb0-5c55ad838788"
        },
        {
          "titulo": "ELIO",
          "horarios": [
            {
              "horario": "11:00",
              "idioma": "Cerrado",
              "formato": "2D"
            }
          ],
          "id": "a6c52069-6635-4671-8276-7bbb60e84d10"
        }
      ],
      "ciudad": "El Alto"
    },
    {
      "peliculas": [
        {
          "titulo": "SUPERMAN",
          "horarios": [
            {
              "horario": "11:00",
              "idioma": "Cerrado",
              "formato": "2D"
            },
            {
              "horario": "12:30",
              "idioma": "Cerrado",
              "formato": "2D"
            },
            {
              "horario": "13:40",
              "idioma": "Cerrado",
              "formato": "2D"
            },
            {
              "horario": "16:20",
              "idioma": "Español",
              "formato": "2D"
            },
            {
              "horario": "19:00",
              "idioma": "Español",
              "formato": "2D"
            },
            {
              "horario": "21:40",
              "idioma": "Español",
              "formato": "2D"
            },
            {
              "horario": "11:30",
              "idioma": "Cerrado",
              "formato": "2D PLUS"
            },
            {
              "horario": "19:30",
              "idioma": "Español",
              "formato": "2D PLUS"
            },
            {
              "horario": "22:10",
              "idioma": "Español",
              "formato": "2D PLUS"
            },
            {
              "horario": "12:50",
              "idioma": "Cerrado",
              "formato": "3D"
            },
            {
              "horario": "15:20",
              "idioma": "Español",
              "formato": "3D"
            },
            {
              "horario": "18:00",
              "idioma": "Español",
              "formato": "3D"
            },
            {
              "horario": "20:40",
              "idioma": "Español",
              "formato": "3D"
            },
            {
              "horario": "14:10",
              "idioma": "Español",
              "formato": "3D PLUS"
            },
            {
              "horario": "16:50",
              "idioma": "Español",
              "formato": "3D PLUS"
            },
            {
              "horario": "19:40",
              "idioma": "Ingles",
              "formato": "2D SUB"
            },
            {
              "horario": "11:30",
              "idioma": "Cerrado",
              "formato": "4D E-MOTION"
            },
            {
              "horario": "14:00",
              "idioma": "Español",
              "formato": "4D E-MOTION"
            },
            {
              "horario": "19:10",
              "idioma": "Español",
              "formato": "4D E-MOTION"
            },
            {
              "horario": "12:00",
              "idioma": "Cerrado",
              "formato": "2D XL"
            },
            {
              "horario": "14:40",
              "idioma": "Español",
              "formato": "2D XL"
            },
            {
              "horario": "17:20",
              "idioma": "Español",
              "formato": "2D XL"
            },
            {
              "horario": "20:00",
              "idioma": "Español",
              "formato": "2D XL"
            },
            {
              "horario": "22:40",
              "idioma": "Español",
              "formato": "2D XL"
            }
          ],
          "id": "cef9dde9-82f7-4d3e-b8cc-04c82a7e24fa"
        },
        {
          "titulo": "JURASSIC WORLD: RENACE",
          "horarios": [
            {
              "horario": "10:20",
              "idioma": "Cerrado",
              "formato": "2D"
            },
            {
              "horario": "11:50",
              "idioma": "Cerrado",
              "formato": "2D"
            },
            {
              "horario": "14:30",
              "idioma": "Español",
              "formato": "2D"
            },
            {
              "horario": "17:10",
              "idioma": "Español",
              "formato": "2D"
            },
            {
              "horario": "19:50",
              "idioma": "Español",
              "formato": "2D"
            },
            {
              "horario": "22:30",
              "idioma": "Español",
              "formato": "2D"
            },
            {
              "horario": "11:00",
              "idioma": "Cerrado",
              "formato": "2D PLUS"
            },
            {
              "horario": "19:20",
              "idioma": "Español",
              "formato": "2D PLUS"
            },
            {
              "horario": "16:30",
              "idioma": "Español",
              "formato": "3D PLUS"
            },
            {
              "horario": "22:10",
              "idioma": "Español",
              "formato": "3D PLUS"
            },
            {
              "horario": "10:30",
              "idioma": "Cerrado",
              "formato": "3D XL"
            },
            {
              "horario": "13:10",
              "idioma": "Cerrado",
              "formato": "3D XL"
            },
            {
              "horario": "16:00",
              "idioma": "Español",
              "formato": "3D XL"
            },
            {
              "horario": "18:50",
              "idioma": "Español",
              "formato": "3D XL"
            },
            {
              "horario": "21:30",
              "idioma": "Español",
              "formato": "3D XL"
            },
            {
              "horario": "16:30",
              "idioma": "Español",
              "formato": "4D E-MOTION"
            },
            {
              "horario": "21:40",
              "idioma": "Español",
              "formato": "4D E-MOTION"
            }
          ],
          "id": "d575a327-ed79-4def-9c45-36eba7299931"
        },
        {
          "titulo": "PITUFOS",
          "horarios": [
            {
              "horario": "10:10",
              "idioma": "Cerrado",
              "formato": "2D"
            },
            {
              "horario": "11:10",
              "idioma": "Cerrado",
              "formato": "2D"
            },
            {
              "horario": "12:20",
              "idioma": "Cerrado",
              "formato": "2D"
            },
            {
              "horario": "13:20",
              "idioma": "Cerrado",
              "formato": "2D"
            },
            {
              "horario": "14:30",
              "idioma": "Español",
              "formato": "2D"
            },
            {
              "horario": "15:30",
              "idioma": "Español",
              "formato": "2D"
            },
            {
              "horario": "16:40",
              "idioma": "Español",
              "formato": "2D"
            },
            {
              "horario": "17:40",
              "idioma": "Español",
              "formato": "2D"
            },
            {
              "horario": "18:50",
              "idioma": "Español",
              "formato": "2D"
            },
            {
              "horario": "19:50",
              "idioma": "Español",
              "formato": "2D"
            },
            {
              "horario": "20:50",
              "idioma": "Español",
              "formato": "2D"
            },
            {
              "horario": "11:45",
              "idioma": "Cerrado",
              "formato": "2D PLUS"
            },
            {
              "horario": "13:50",
              "idioma": "Español",
              "formato": "2D PLUS"
            },
            {
              "horario": "16:00",
              "idioma": "Español",
              "formato": "2D PLUS"
            },
            {
              "horario": "18:10",
              "idioma": "Español",
              "formato": "2D PLUS"
            }
          ],
          "id": "7d985bde-967b-49b8-9eec-77576e44a9de"
        },
        {
          "titulo": "COMO ENTRENAR A TU DRAGÓN",
          "horarios": [
            {
              "horario": "10:00",
              "idioma": "Cerrado",
              "formato": "2D"
            },
            {
              "horario": "12:20",
              "idioma": "Cerrado",
              "formato": "2D"
            },
            {
              "horario": "14:50",
              "idioma": "Español",
              "formato": "2D"
            },
            {
              "horario": "16:20",
              "idioma": "Español",
              "formato": "2D"
            },
            {
              "horario": "17:20",
              "idioma": "Español",
              "formato": "2D"
            },
            {
              "horario": "19:50",
              "idioma": "Español",
              "formato": "2D"
            },
            {
              "horario": "22:20",
              "idioma": "Español",
              "formato": "2D"
            },
            {
              "horario": "13:50",
              "idioma": "Español",
              "formato": "2D PLUS"
            }
          ],
          "id": "89155ab0-b1a2-4bbe-90be-1f122db9ae7b"
        },
        {
          "titulo": "SÉ LO QUE HICIERON EL VERANO PASADO",
          "horarios": [
            {
              "horario": "10:20",
              "idioma": "Cerrado",
              "formato": "2D"
            },
            {
              "horario": "12:50",
              "idioma": "Cerrado",
              "formato": "2D"
            },
            {
              "horario": "15:15",
              "idioma": "Español",
              "formato": "2D"
            },
            {
              "horario": "17:45",
              "idioma": "Español",
              "formato": "2D"
            },
            {
              "horario": "20:10",
              "idioma": "Español",
              "formato": "2D"
            },
            {
              "horario": "22:40",
              "idioma": "Español",
              "formato": "2D"
            }
          ],
          "id": "04d184eb-f6f1-44d4-96c3-707849b973d7"
        },
        {
          "titulo": "LILO & STITCH",
          "horarios": [
            {
              "horario": "17:15",
              "idioma": "Español",
              "formato": "2D"
            },
            {
              "horario": "18:50",
              "idioma": "Español",
              "formato": "2D"
            },
            {
              "horario": "21:00",
              "idioma": "Español",
              "formato": "2D"
            },
            {
              "horario": "22:45",
              "idioma": "Español",
              "formato": "2D"
            }
          ],
          "id": "54eaac66-627e-4af9-b760-a9d19f3ae083"
        },
        {
          "titulo": "F1: LA PELÍCULA",
          "horarios": [
            {
              "horario": "13:10",
              "idioma": "Cerrado",
              "formato": "2D"
            },
            {
              "horario": "20:20",
              "idioma": "Español",
              "formato": "2D PLUS"
            }
          ],
          "id": "a74e8a4a-9d1a-40b6-a22b-ef84ab09c681"
        },
        {
          "titulo": "ELIO",
          "horarios": [
            {
              "horario": "15:10",
              "idioma": "Español",
              "formato": "2D"
            }
          ],
          "id": "a6c52069-6635-4671-8276-7bbb60e84d10"
        },
        {
          "titulo": "EXTERMINIO: LA EVOLUCIÓN",
          "horarios": [
            {
              "horario": "22:15",
              "idioma": "Español",
              "formato": "2D"
            }
          ],
          "id": "f0f188a2-9913-4b60-92da-217a96675db5"
        },
        {
          "titulo": "INVASIÓN ZOMBIE: HIJOS DEL APOCALÍPSIS",
          "horarios": [
            {
              "horario": "21:50",
              "idioma": "Español",
              "formato": "2D"
            }
          ],
          "id": "caa7e991-4b8a-4972-bbb0-5c55ad838788"
        }
      ],
      "ciudad": "La Paz"
    },
    {
      "peliculas": [
        {
          "titulo": "JURASSIC WORLD: RENACE",
          "horarios": [
            {
              "horario": "10:10",
              "idioma": "Cerrado",
              "formato": "2D"
            },
            {
              "horario": "11:20",
              "idioma": "Cerrado",
              "formato": "2D"
            },
            {
              "horario": "12:20",
              "idioma": "Cerrado",
              "formato": "2D"
            },
            {
              "horario": "14:00",
              "idioma": "Español",
              "formato": "2D"
            },
            {
              "horario": "15:00",
              "idioma": "Español",
              "formato": "2D"
            },
            {
              "horario": "16:40",
              "idioma": "Español",
              "formato": "2D"
            },
            {
              "horario": "17:40",
              "idioma": "Español",
              "formato": "2D"
            },
            {
              "horario": "19:20",
              "idioma": "Español",
              "formato": "2D"
            },
            {
              "horario": "20:15",
              "idioma": "Español",
              "formato": "2D"
            },
            {
              "horario": "22:00",
              "idioma": "Español",
              "formato": "2D"
            },
            {
              "horario": "22:50",
              "idioma": "Ingles",
              "formato": "2D SUB"
            }
          ],
          "id": "d575a327-ed79-4def-9c45-36eba7299931"
        },
        {
          "titulo": "SUPERMAN",
          "horarios": [
            {
              "horario": "10:00",
              "idioma": "Cerrado",
              "formato": "2D"
            },
            {
              "horario": "11:00",
              "idioma": "Cerrado",
              "formato": "2D"
            },
            {
              "horario": "16:20",
              "idioma": "Español",
              "formato": "2D"
            },
            {
              "horario": "19:00",
              "idioma": "Español",
              "formato": "2D"
            },
            {
              "horario": "21:40",
              "idioma": "Español",
              "formato": "2D"
            },
            {
              "horario": "12:00",
              "idioma": "Cerrado",
              "formato": "2D XL"
            },
            {
              "horario": "14:40",
              "idioma": "Español",
              "formato": "2D XL"
            },
            {
              "horario": "17:20",
              "idioma": "Español",
              "formato": "2D XL"
            },
            {
              "horario": "20:00",
              "idioma": "Español",
              "formato": "2D XL"
            },
            {
              "horario": "22:40",
              "idioma": "Español",
              "formato": "2D XL"
            },
            {
              "horario": "13:40",
              "idioma": "Cerrado",
              "formato": "3D"
            },
            {
              "horario": "17:30",
              "idioma": "Ingles",
              "formato": "2D SUB"
            },
            {
              "horario": "20:10",
              "idioma": "Ingles",
              "formato": "2D SUB"
            }
          ],
          "id": "cef9dde9-82f7-4d3e-b8cc-04c82a7e24fa"
        },
        {
          "titulo": "PITUFOS",
          "horarios": [
            {
              "horario": "10:10",
              "idioma": "Cerrado",
              "formato": "2D"
            },
            {
              "horario": "11:10",
              "idioma": "Cerrado",
              "formato": "2D"
            },
            {
              "horario": "12:20",
              "idioma": "Cerrado",
              "formato": "2D"
            },
            {
              "horario": "13:20",
              "idioma": "Cerrado",
              "formato": "2D"
            },
            {
              "horario": "14:30",
              "idioma": "Español",
              "formato": "2D"
            },
            {
              "horario": "15:30",
              "idioma": "Español",
              "formato": "2D"
            },
            {
              "horario": "16:40",
              "idioma": "Español",
              "formato": "2D"
            },
            {
              "horario": "18:45",
              "idioma": "Español",
              "formato": "2D"
            },
            {
              "horario": "20:45",
              "idioma": "Español",
              "formato": "2D"
            }
          ],
          "id": "7d985bde-967b-49b8-9eec-77576e44a9de"
        },
        {
          "titulo": "COMO ENTRENAR A TU DRAGÓN",
          "horarios": [
            {
              "horario": "10:00",
              "idioma": "Cerrado",
              "formato": "2D"
            },
            {
              "horario": "12:45",
              "idioma": "Cerrado",
              "formato": "2D"
            },
            {
              "horario": "15:20",
              "idioma": "Español",
              "formato": "2D"
            },
            {
              "horario": "18:00",
              "idioma": "Español",
              "formato": "2D"
            },
            {
              "horario": "20:30",
              "idioma": "Español",
              "formato": "2D"
            }
          ],
          "id": "89155ab0-b1a2-4bbe-90be-1f122db9ae7b"
        },
        {
          "titulo": "SÉ LO QUE HICIERON EL VERANO PASADO",
          "horarios": [
            {
              "horario": "12:50",
              "idioma": "Cerrado",
              "formato": "2D"
            },
            {
              "horario": "17:20",
              "idioma": "Español",
              "formato": "2D"
            },
            {
              "horario": "19:45",
              "idioma": "Español",
              "formato": "2D"
            },
            {
              "horario": "22:10",
              "idioma": "Español",
              "formato": "2D"
            }
          ],
          "id": "04d184eb-f6f1-44d4-96c3-707849b973d7"
        },
        {
          "titulo": "LILO & STITCH",
          "horarios": [
            {
              "horario": "16:10",
              "idioma": "Español",
              "formato": "2D"
            },
            {
              "horario": "18:30",
              "idioma": "Español",
              "formato": "2D"
            }
          ],
          "id": "54eaac66-627e-4af9-b760-a9d19f3ae083"
        },
        {
          "titulo": "F1: LA PELÍCULA",
          "horarios": [
            {
              "horario": "13:00",
              "idioma": "Cerrado",
              "formato": "2D"
            },
            {
              "horario": "20:45",
              "idioma": "Español",
              "formato": "2D"
            }
          ],
          "id": "a74e8a4a-9d1a-40b6-a22b-ef84ab09c681"
        },
        {
          "titulo": "ELIO",
          "horarios": [
            {
              "horario": "15:10",
              "idioma": "Español",
              "formato": "2D"
            }
          ],
          "id": "a6c52069-6635-4671-8276-7bbb60e84d10"
        },
        {
          "titulo": "EXTERMINIO: LA EVOLUCIÓN",
          "horarios": [
            {
              "horario": "22:40",
              "idioma": "Español",
              "formato": "2D"
            }
          ],
          "id": "f0f188a2-9913-4b60-92da-217a96675db5"
        },
        {
          "titulo": "INVASIÓN ZOMBIE: HIJOS DEL APOCALÍPSIS",
          "horarios": [
            {
              "horario": "22:45",
              "idioma": "Español",
              "formato": "2D"
            }
          ],
          "id": "caa7e991-4b8a-4972-bbb0-5c55ad838788"
        }
      ],
      "ciudad": "Santa Cruz"
    }
  ],
  "cine": "MULTICINE",
  "fecha": "18/7/2025"
}